bhv/__init__.py
bhv/abstract.py
bhv/embedding.py
bhv/lookup.py
bhv/np.py
bhv/poibin.py
bhv/positions.py
bhv/pytorch.py
bhv/shared.py
bhv/slice.py
bhv/symbolic.py
bhv/test.py
bhv/unification.py
bhv/vanilla.py
bhv/visualization.py
bhv-0.4.4.dist-info/LICENSE
bhv-0.4.4.dist-info/METADATA
bhv-0.4.4.dist-info/WHEEL
bhv-0.4.4.dist-info/top_level.txt
bhv-0.4.4.dist-info/RECORD
