Metadata-Version: 2.1
Name: bhv
Version: 0.4.4
Summary: Boolean Hypervectors
Home-page: https://github.com/Adam-Vandervorst/PyBHV
Author: Adam Vandervorst
Author-email: contact@adamv.be
Keywords: ai binary hypervector hdc bsc
Classifier: Development Status :: 2 - Pre-Alpha
Classifier: Intended Audience :: Developers
Classifier: Intended Audience :: Science/Research
Classifier: Topic :: Scientific/Engineering :: Artificial Intelligence
Classifier: Topic :: Software Development :: Libraries
Classifier: License :: Free for non-commercial use
Classifier: Environment :: GPU :: NVIDIA CUDA
Classifier: Operating System :: POSIX :: Linux
Classifier: Programming Language :: Python :: 3.8
Classifier: Programming Language :: Python :: 3.9
Classifier: Programming Language :: Python :: 3.10
Classifier: Programming Language :: Python :: 3.11
Classifier: Typing :: Typed
Requires-Python: >=3.8
License-File: LICENSE
Provides-Extra: numpy
Requires-Dist: numpy (>=1.24.2) ; extra == 'numpy'
Provides-Extra: torch
Requires-Dist: torch (>=2.0.0) ; extra == 'torch'
